LICENSE
LICENSE.txt
README.rst
setup.cfg
setup.py
myaekps1/__init__.py
myaekps1/myae1.py
myaekps1.egg-info/PKG-INFO
myaekps1.egg-info/SOURCES.txt
myaekps1.egg-info/dependency_links.txt
myaekps1.egg-info/top_level.txt